{"runes":[{"category":"Inspiration","atributes":[{"id":"8351","name":"Glacial Augment"},{"id":"8304","name":"Magical Footwear"},{"id":"8345","name":"Biscuit Delivery"},{"id":"8347","name":"Cosmic Insight"}]},{"category":"Resolve","atributes":[{"id":"8463","name":"Font of Life"},{"id":"8453","name":"Revitalize"}]}],"skills":{"q":[1,0,0,0,0,0,0,0,0,0,0,0,0,14,15,0,17,18],"w":[0,0,3,0,0,0,0,8,0,10,0,12,13,0,0,0,0,0],"e":[0,2,0,4,5,0,7,0,9,0,0,0,0,0,0,0,0,0],"r":[0,0,0,0,0,6,0,0,0,0,11,0,0,0,0,16,0,0]},"spells":["Exhaust","Flash"],"build":{"starter":[{"id":"3850","name":"Spellthief's Edge"},{"id":"2003","name":"Health Potion"},{"id":"3340","name":"Stealth Ward"}],"early":[{"id":"4642","name":"Bandleglass Mirror"},{"id":"2055","name":"Control Ward"}],"core":[{"id":"3853","name":"Shard of True Ice"},{"id":"3158","name":"Ionian Boots of Lucidity"},{"id":"2065","name":"Shurelya's Battlesong"}],"full":[{"id":"3853","name":"Shard of True Ice"},{"id":"3158","name":"Ionian Boots of Lucidity"},{"id":"2065","name":"Shurelya's Battlesong"},{"id":"3504","name":"Ardent Censer"},{"id":"3107","name":"Redemption"},{"id":"4643","name":"Vigilant Wardstone"}],"situational":[{"id":"6616","name":"Staff of Flowing Water"},{"id":"3011","name":"Chemtech Putrifier"},{"id":"4005","name":"Imperial Mandate"},{"id":"3222","name":"Mikael's Blessing"},{"id":"3041","name":"Mejai's Soulstealer"},{"id":"3157","name":"Zhonya's Hourglass"}]},"status":{"tier":"S","winrate":52.4,"pickrate":5.1,"banrate":1.1,"matches":132184}}